saiblo_upload/__init__.py
saiblo_upload/__main__.py
saiblo_upload-0.0.4.dist-info/LICENSE
saiblo_upload-0.0.4.dist-info/METADATA
saiblo_upload-0.0.4.dist-info/WHEEL
saiblo_upload-0.0.4.dist-info/entry_points.txt
saiblo_upload-0.0.4.dist-info/top_level.txt
saiblo_upload-0.0.4.dist-info/RECORD
