Metadata-Version: 2.1
Name: saiblo-upload
Version: 0.0.4
Summary: Saiblo AI 代码上传脚本
Home-page: https://github.com/saiblo/saiblo-upload
Author: UNIDY2002
Author-email: UNIDY2002@outlook.com
Classifier: Programming Language :: Python :: 3
Classifier: License :: OSI Approved :: MIT License
Classifier: Operating System :: OS Independent
License-File: LICENSE
Requires-Dist: requests
Requires-Dist: websockets
